{
  "titulo": "Acerca de",
  "info": "En este apartado vienen resueltas las (hipot칠ticas) preguntas frecuentemente preguntadas para cualquier persona que pueda tener estas dudas.",
  "question1": "쯄e estas robando la informaci칩n?",
  "answer1": "No! pero si no me crees puedes ver el c칩digo en el repositorio, sin embargo si no eres un nerd solo puedes confiar en mi palabra, solo quiero a침adir que hice esta aplicaci칩n en mi tiempo libre sin ning칰n tipo de mala intencion 游.",
  "repoLink": "Link del repositorio.",
  "question2": "Como funciona?",
  "answer2": ""
}
